doy/.unused.py
doy/__init__.py
doy/data.py
doy/kv.py
doy/logger.py
doy/plotting.py
doy/progress.py
doy/proquint.py
doy/rich_utils.py
doy/utils.py
doy-1.9.2.dist-info/WHEEL
doy-1.9.2.dist-info/METADATA
doy-1.9.2.dist-info/RECORD
