Metadata-Version: 2.1
Name: doy
Version: 1.9.2
Summary: 
Author: Dominik Schmidt
Author-email: schmidtdominik30@gmail.com
Requires-Python: >=3.8
Classifier: Programming Language :: Python :: 3
Classifier: Programming Language :: Python :: 3.8
Classifier: Programming Language :: Python :: 3.9
Classifier: Programming Language :: Python :: 3.10
Requires-Dist: filelock (>=3.12.2,<4.0.0)
Requires-Dist: matplotlib (>=3.6.2)
Requires-Dist: numpy
Requires-Dist: rich (>=13.4.1)
Requires-Dist: tqdm (>=4.65.0)
Requires-Dist: wandb (>=0.15.5)
